geocodeus.py
geocodeus-22.0.dist-info/METADATA
geocodeus-22.0.dist-info/WHEEL
geocodeus-22.0.dist-info/top_level.txt
geocodeus-22.0.dist-info/RECORD
