Metadata-Version: 2.1
Name: geocodeus
Version: 22.0
Summary: A Python package for converting US zip codes to latitude and longitude
Author: Sam Mathew
Author-email: sammathew000@gmail.com
